gcn_manager/__init__.py
gcn_manager/__main__.py
gcn_manager/brain.py
gcn_manager/constants.py
gcn_manager/mqtt.py
gcn_manager/notifiers.py
gcn_manager-1.0.6.dist-info/licenses/LICENSE
gcn_manager-1.0.6.dist-info/METADATA
gcn_manager-1.0.6.dist-info/WHEEL
gcn_manager-1.0.6.dist-info/top_level.txt
gcn_manager-1.0.6.dist-info/RECORD
