Metadata-Version: 2.4
Name: gcn-manager
Version: 1.0.6
Summary: Management application for mqtt-based gpio-change-notifier clients
Author-email: nipil <nipil@users.noreply.github.com>
License-Expression: MIT
Project-URL: Homepage, https://github.com/nipil/gcn-manager-py
Project-URL: Issues, https://github.com/nipil/gcn-manager-py/issues
Classifier: Programming Language :: Python :: 3
Classifier: Operating System :: OS Independent
Requires-Python: >=3.11
License-File: LICENSE
Requires-Dist: backoff==2.2.1
Requires-Dist: dotenv==0.9.9
Requires-Dist: email_validator==2.2.0
Requires-Dist: ovh==1.2.0
Requires-Dist: paho-mqtt==2.1.0
Requires-Dist: phonenumbers==9.0.8
Requires-Dist: pydantic==2.11.7
Requires-Dist: tweepy==4.16.0
Requires-Dist: aiohappyeyeballs==2.6.1
Requires-Dist: aiohttp==3.12.13
Requires-Dist: aiosignal==1.4.0
Requires-Dist: annotated-types==0.7.0
Requires-Dist: async-lru==2.0.5
Requires-Dist: attrs==25.3.0
Requires-Dist: certifi==2025.6.15
Requires-Dist: charset-normalizer==3.4.2
Requires-Dist: dnspython==2.7.0
Requires-Dist: frozenlist==1.7.0
Requires-Dist: idna==3.10
Requires-Dist: multidict==6.6.3
Requires-Dist: oauthlib==3.3.1
Requires-Dist: propcache==0.3.2
Requires-Dist: pydantic_core==2.33.2
Requires-Dist: python-dotenv==1.1.1
Requires-Dist: requests==2.32.4
Requires-Dist: requests-oauthlib==2.0.0
Requires-Dist: typing-inspection==0.4.1
Requires-Dist: typing_extensions==4.14.1
Requires-Dist: urllib3==2.5.0
Requires-Dist: yarl==1.20.1
Dynamic: license-file
